remfile/DiskCache.py
remfile/RemFile.py
remfile/__init__.py
remfile-0.1.13.dist-info/LICENSE
remfile-0.1.13.dist-info/METADATA
remfile-0.1.13.dist-info/WHEEL
remfile-0.1.13.dist-info/top_level.txt
remfile-0.1.13.dist-info/RECORD
