Metadata-Version: 2.1
Name: remfile
Version: 0.1.13
Summary: File-like object from url of remote file, optimized for use with h5py.
Home-page: https://github.com/magland/remfile
Author: Jeremy Magland
Author-email: jmagland@flatironinstitute.org
License-File: LICENSE
Requires-Dist: numpy
Requires-Dist: h5py
Requires-Dist: requests
